Reff/Reff.py
Reff/__init__.py
Reff-0.0.2.dist-info/LICENSE
Reff-0.0.2.dist-info/METADATA
Reff-0.0.2.dist-info/WHEEL
Reff-0.0.2.dist-info/top_level.txt
Reff-0.0.2.dist-info/RECORD
