Metadata-Version: 2.1
Name: Reff
Version: 0.0.2
Summary: effective reproduction number
Home-page: https://github.com/tt-nakamura/Reff
Author: Takahiro Nakamura
Author-email: a41757@gmail.com
License: UNKNOWN
Platform: UNKNOWN
Classifier: Programming Language :: Python :: 3
Classifier: License :: OSI Approved :: MIT License
Classifier: Operating System :: OS Independent
Requires-Python: >=3.6
